text_me_keras/callbacks/__init__.py
text_me_keras/callbacks/texting.py
text_me_keras/messaging/__init__.py
text_me_keras/messaging/sms.py
text_me_keras-0.1.1.dist-info/METADATA
text_me_keras-0.1.1.dist-info/WHEEL
text_me_keras-0.1.1.dist-info/top_level.txt
text_me_keras-0.1.1.dist-info/RECORD
