Metadata-Version: 2.1
Name: text-me-keras
Version: 0.1.1
Summary: A TenosorFlow callback that texts you back (to let you know how training is going).
Home-page: https://github.com/djvaroli/text_me_keras
Author: Daniel John Varoli
Author-email: daniel.varoli@gmail.com
License: UNKNOWN
Platform: UNKNOWN
Classifier: Programming Language :: Python :: 3
Classifier: Operating System :: OS Independent
Requires-Dist: tensorflow (>=2.7.0)
Requires-Dist: twilio (==7.6.0)
